tuskar-0.4.18.dist-info/WHEEL
tuskar-0.4.18.dist-info/metadata.json
tuskar-0.4.18.dist-info/entry_points.txt
tuskar-0.4.18.dist-info/METADATA
tuskar-0.4.18.dist-info/dependency_links.txt
tuskar-0.4.18.dist-info/RECORD
tuskar-0.4.18.dist-info/DESCRIPTION.rst
tuskar-0.4.18.dist-info/pbr.json
tuskar-0.4.18.dist-info/top_level.txt
tuskar/netconf.py
tuskar/__init__.py
tuskar/version.py
tuskar/db/__init__.py
tuskar/db/api.py
tuskar/db/migration.py
tuskar/db/sqlalchemy/models.py
tuskar/db/sqlalchemy/__init__.py
tuskar/db/sqlalchemy/api.py
tuskar/db/sqlalchemy/migration.py
tuskar/db/sqlalchemy/migrate_repo/migrate.cfg
tuskar/db/sqlalchemy/migrate_repo/__init__.py
tuskar/db/sqlalchemy/migrate_repo/manage.py
tuskar/db/sqlalchemy/migrate_repo/versions/001_init.py
tuskar/db/sqlalchemy/migrate_repo/versions/002_add_stored_file.py
tuskar/db/sqlalchemy/migrate_repo/versions/__init__.py
tuskar/db/sqlalchemy/migrate_repo/versions/003_add_relative_path.py
tuskar/db/sqlalchemy/migrate_repo/versions/004_add_registry_path.py
tuskar/heat/template_tools.py
tuskar/heat/__init__.py
tuskar/heat/client.py
tuskar/common/config.py
tuskar/common/exception.py
tuskar/common/__init__.py
tuskar/common/service.py
tuskar/common/paths.py
tuskar/common/utils.py
tuskar/manager/role.py
tuskar/manager/name_utils.py
tuskar/manager/models.py
tuskar/manager/__init__.py
tuskar/manager/plan.py
tuskar/cmd/delete_roles.py
tuskar/cmd/load_role.py
tuskar/cmd/dbsync.py
tuskar/cmd/__init__.py
tuskar/cmd/load_seed.py
tuskar/cmd/api.py
tuskar/cmd/load_roles.py
tuskar/openstack/__init__.py
tuskar/openstack/common/gettextutils.py
tuskar/openstack/common/jsonutils.py
tuskar/openstack/common/timeutils.py
tuskar/openstack/common/log.py
tuskar/openstack/common/__init__.py
tuskar/openstack/common/local.py
tuskar/openstack/common/importutils.py
tuskar/openstack/common/strutils.py
tuskar/openstack/common/config/generator.py
tuskar/openstack/common/config/__init__.py
tuskar/api/config.py
tuskar/api/app.py
tuskar/api/__init__.py
tuskar/api/renderers.py
tuskar/api/hooks.py
tuskar/api/acl.py
tuskar/api/controllers/root.py
tuskar/api/controllers/__init__.py
tuskar/api/controllers/v2/controller.py
tuskar/api/controllers/v2/roles.py
tuskar/api/controllers/v2/types.py
